HISTORY.rst
MANIFEST.in
README.rst
setup.py
towbar/__init__.py
towbar/towbar.py
towbar.egg-info/PKG-INFO
towbar.egg-info/SOURCES.txt
towbar.egg-info/dependency_links.txt
towbar.egg-info/requires.txt
towbar.egg-info/top_level.txt