Metadata-Version: 1.0
Name: towbar
Version: 0.1.1
Summary: Python library for the boxcar.io API
Home-page: https://github.com/mrtazz/towbar
Author: Daniel Schauenberg
Author-email: d@unwiredcouch.com
License: MIT
Platform: UNKNOWN
Classifier: Development Status :: 4 - Beta
Classifier: License :: OSI Approved :: MIT License
Classifier: Programming Language :: Python
Classifier: Programming Language :: Python :: 2.5
Classifier: Programming Language :: Python :: 2.6
Classifier: Programming Language :: Python :: 2.7
